datapungi_imf/__init__.py
datapungi_imf/api.py
datapungi_imf/driverCore.py
datapungi_imf/drivers.py
datapungi_imf/generalSettings.py
datapungi_imf/sampler.py
datapungi_imf/utils.py
datapungi_imf/config/__init__.py
datapungi_imf/config/datasetlist.yaml
datapungi_imf/config/pkgConfig.yaml
datapungi_imf/config/userSettings.json
datapungi_imf/tests/__init__.py
datapungi_imf/tests/conftest.py
datapungi_imf/tests/main.py
datapungi_imf/tests/test_drivers.py
datapungi_imf/tests/test_driversCI.py
datapungi_imf-0.2.0.dist-info/LICENSE
datapungi_imf-0.2.0.dist-info/WHEEL
datapungi_imf-0.2.0.dist-info/METADATA
datapungi_imf-0.2.0.dist-info/RECORD
